MANIFEST.in
requirements.txt
setup.py
captureth/__init__.py
captureth/app.py
captureth/capture_service.py
captureth.egg-info/PKG-INFO
captureth.egg-info/SOURCES.txt
captureth.egg-info/dependency_links.txt
captureth.egg-info/requires.txt
captureth.egg-info/top_level.txt