Metadata-Version: 1.0
Name: captureth
Version: 0.0.5
Summary: Capture msgs from pyethapp
Home-page: http://github.com/Consensys/pycaptureth/
Author: UNKNOWN
Author-email: UNKNOWN
License: MIT
Platform: UNKNOWN
